CHANGES.rst
LICENSE
MANIFEST.in
README.rst
dirtools.py
setup.py
test_dirtools.py
dirtools.egg-info/PKG-INFO
dirtools.egg-info/SOURCES.txt
dirtools.egg-info/dependency_links.txt
dirtools.egg-info/requires.txt
dirtools.egg-info/top_level.txt