Metadata-Version: 1.1
Name: dirtools
Version: 0.1.0
Summary: Description
Home-page: https://github.com/tsileo/dirtools
Author: Thomas Sileo
Author-email: thomas.sileo@gmail.com
License: MIT
Keywords: some keyword
Platform: UNKNOWN
Classifier: Development Status :: 4 - Beta
Classifier: Intended Audience :: Developers
Classifier: License :: OSI Approved :: MIT License
Classifier: Programming Language :: Python
